<metadata xml:lang="en">
	<eainfo>
		<detailed Name="_BenthicPointCoverCodeBySite_Coral">
			<enttyp>
				<enttypl Sync="TRUE">_BenthicPointCoverCodeBySite_Coral</enttypl>
				<enttypt Sync="TRUE">Feature Class</enttypt>
				<enttypc Sync="TRUE">8</enttypc>
			</enttyp>
			<attr>
				<attrlabl Sync="TRUE">FID</attrlabl>
				<attalias Sync="TRUE">FID</attalias>
				<attrtype Sync="TRUE">OID</attrtype>
				<attwidth Sync="TRUE">4</attwidth>
				<atprecis Sync="TRUE">0</atprecis>
				<attscale Sync="TRUE">0</attscale>
				<attrdef Sync="TRUE">Internal feature number.</attrdef>
				<attrdefs Sync="TRUE">Esri</attrdefs>
				<attrdomv>
					<udom Sync="TRUE">Sequential unique whole numbers that are automatically generated.</udom>
				</attrdomv>
			</attr>
			<attr>
				<attrlabl Sync="TRUE">Shape</attrlabl>
				<attalias Sync="TRUE">Shape</attalias>
				<attrtype Sync="TRUE">Geometry</attrtype>
				<attwidth Sync="TRUE">0</attwidth>
				<atprecis Sync="TRUE">0</atprecis>
				<attscale Sync="TRUE">0</attscale>
				<attrdef Sync="TRUE">Feature geometry.</attrdef>
				<attrdefs Sync="TRUE">Esri</attrdefs>
				<attrdomv>
					<udom Sync="TRUE">Coordinates defining the features.</udom>
				</attrdomv>
			</attr>
			
			<attr>
				<attrlabl Sync="TRUE">BATCH</attrlabl>
				<attalias Sync="TRUE">BATCH</attalias>
				<attrtype Sync="TRUE">String</attrtype>
				<attwidth Sync="TRUE">255</attwidth>
				<atprecis Sync="TRUE">0</atprecis>
				<attscale Sync="TRUE">0</attscale>
				<attrdefs Sync="TRUE">AGRRA</attrdefs>
				<attrdomv>
					<udom Sync="TRUE">Name of batch</udom>
				</attrdomv>
			</attr>
			
			<attr>
				<attrlabl Sync="TRUE">CODE</attrlabl>
				<attalias Sync="TRUE">CODE</attalias>
				<attrtype Sync="TRUE">String</attrtype>
				<attwidth Sync="TRUE">255</attwidth>
				<atprecis Sync="TRUE">0</atprecis>
				<attscale Sync="TRUE">0</attscale>
				<attrdefs Sync="TRUE">AGRRA</attrdefs>
				<attrdomv>
					<udom Sync="TRUE">Site code</udom>
				</attrdomv>
			</attr>
			
			<attr>
				<attrlabl Sync="TRUE">SITE</attrlabl>
				<attalias Sync="TRUE">SITE</attalias>
				<attrtype Sync="TRUE">String</attrtype>
				<attwidth Sync="TRUE">255</attwidth>
				<atprecis Sync="TRUE">0</atprecis>
				<attscale Sync="TRUE">0</attscale>
				<attrdefs Sync="TRUE">AGRRA</attrdefs>
				<attrdomv>
					<udom Sync="TRUE">Name of site</udom>
				</attrdomv>
			</attr>
			
			<attr>
				<attrlabl Sync="TRUE">DATE</attrlabl>
				<attalias Sync="TRUE">DATE</attalias>
				<attrtype Sync="TRUE">String</attrtype>
				<attwidth Sync="TRUE">19</attwidth>
				<atprecis Sync="TRUE">0</atprecis>
				<attscale Sync="TRUE">0</attscale>
				<attrdefs Sync="TRUE">AGRRA</attrdefs>
				<attrdomv>
					<udom Sync="TRUE">Date of survey</udom>
				</attrdomv>
			</attr>
			
			<attr>
				<attrlabl Sync="TRUE">LATITUDE</attrlabl>
				<attalias Sync="TRUE">LATITUDE</attalias>
				<attrtype Sync="TRUE">String</attrtype>
				<attwidth Sync="TRUE">24</attwidth>
				<atprecis Sync="TRUE">0</atprecis>
				<attscale Sync="TRUE">0</attscale>
				<attrdefs Sync="TRUE">AGRRA</attrdefs>
				<attrdomv>
					<udom Sync="TRUE">Latitude (in decimal degrees)</udom>
				</attrdomv>
			</attr>
			
			<attr>
				<attrlabl Sync="TRUE">LONGITUDE</attrlabl>
				<attalias Sync="TRUE">LONGITUDE</attalias>
				<attrtype Sync="TRUE">String</attrtype>
				<attwidth Sync="TRUE">24</attwidth>
				<atprecis Sync="TRUE">0</atprecis>
				<attscale Sync="TRUE">0</attscale>
				<attrdefs Sync="TRUE">AGRRA</attrdefs>
				<attrdomv>
					<udom Sync="TRUE">Longitude (in decimal degrees)</udom>
				</attrdomv>
			</attr>
			
			<attr>
				<attrlabl Sync="TRUE">ZONE</attrlabl>
				<attalias Sync="TRUE">ZONE</attalias>
				<attrtype Sync="TRUE">String</attrtype>
				<attwidth Sync="TRUE">255</attwidth>
				<atprecis Sync="TRUE">0</atprecis>
				<attscale Sync="TRUE">0</attscale>
				<attrdefs Sync="TRUE">AGRRA</attrdefs>
				<attrdomv>
					<udom Sync="TRUE">Reef zone category</udom>
				</attrdomv>
			</attr>
			
			<attr>
				<attrlabl Sync="TRUE">SUBREGION</attrlabl>
				<attalias Sync="TRUE">SUBREGION</attalias>
				<attrtype Sync="TRUE">String</attrtype>
				<attwidth Sync="TRUE">255</attwidth>
				<atprecis Sync="TRUE">0</atprecis>
				<attscale Sync="TRUE">0</attscale>
				<attrdefs Sync="TRUE">AGRRA</attrdefs>
				<attrdomv>
					<udom Sync="TRUE">Region within country</udom>
				</attrdomv>
			</attr>
			
			<attr>
				<attrlabl Sync="TRUE">SHELF</attrlabl>
				<attalias Sync="TRUE">SHELF</attalias>
				<attrtype Sync="TRUE">String</attrtype>
				<attwidth Sync="TRUE">255</attwidth>
				<atprecis Sync="TRUE">0</atprecis>
				<attscale Sync="TRUE">0</attscale>
				<attrdefs Sync="TRUE">AGRRA</attrdefs>
				<attrdomv>
					<udom Sync="TRUE">Continental/insular shelf unit</udom>
				</attrdomv>
			</attr>
			
			<attr>
				<attrlabl Sync="TRUE">ECOREGION</attrlabl>
				<attalias Sync="TRUE">ECOREGION</attalias>
				<attrtype Sync="TRUE">String</attrtype>
				<attwidth Sync="TRUE">255</attwidth>
				<atprecis Sync="TRUE">0</atprecis>
				<attscale Sync="TRUE">0</attscale>
				<attrdefs Sync="TRUE">AGRRA</attrdefs>
				<attrdomv>
					<udom Sync="TRUE">Marine ecoregional classification</udom>
				</attrdomv>
			</attr>
			
			<attr>
				<attrlabl Sync="TRUE">DEPTH</attrlabl>
				<attalias Sync="TRUE">DEPTH</attalias>
				<attrtype Sync="TRUE">String</attrtype>
				<attwidth Sync="TRUE">24</attwidth>
				<atprecis Sync="TRUE">0</atprecis>
				<attscale Sync="TRUE">0</attscale>
				<attrdefs Sync="TRUE">AGRRA</attrdefs>
				<attrdomv>
					<udom Sync="TRUE">Average depth of survey (meters)</udom>
				</attrdomv>
			</attr>
			
			<attr>
				<attrlabl Sync="TRUE">NT</attrlabl>
				<attalias Sync="TRUE">NT</attalias>
				<attrtype Sync="TRUE">String</attrtype>
				<attwidth Sync="TRUE">10</attwidth>
				<atprecis Sync="TRUE">0</atprecis>
				<attscale Sync="TRUE">0</attscale>
				<attrdefs Sync="TRUE">AGRRA</attrdefs>
				<attrdomv>
					<udom Sync="TRUE">Total number of transects</udom>
				</attrdomv>
			</attr>
			
			<attr>
				<attrlabl Sync="TRUE">LCAVG</attrlabl>
				<attalias Sync="TRUE">LCAVG</attalias>
				<attrtype Sync="TRUE">String</attrtype>
				<attwidth Sync="TRUE">24</attwidth>
				<atprecis Sync="TRUE">0</atprecis>
				<attscale Sync="TRUE">0</attscale>
				<attrdefs Sync="TRUE">AGRRA</attrdefs>
				<attrdomv>
					<udom Sync="TRUE">Transect Average of % Uncategorized Live Coral</udom>
				</attrdomv>
			</attr>
			
			<attr>
				<attrlabl Sync="TRUE">LCSTD</attrlabl>
				<attalias Sync="TRUE">LCSTD</attalias>
				<attrtype Sync="TRUE">String</attrtype>
				<attwidth Sync="TRUE">24</attwidth>
				<atprecis Sync="TRUE">0</atprecis>
				<attscale Sync="TRUE">0</attscale>
				<attrdefs Sync="TRUE">AGRRA</attrdefs>
				<attrdomv>
					<udom Sync="TRUE">Transect Std. Deviation of % Uncategorized Live Coral</udom>
				</attrdomv>
			</attr>
			
			<attr>
				<attrlabl Sync="TRUE">AAGAAVG</attrlabl>
				<attalias Sync="TRUE">AAGAAVG</attalias>
				<attrtype Sync="TRUE">String</attrtype>
				<attwidth Sync="TRUE">24</attwidth>
				<atprecis Sync="TRUE">0</atprecis>
				<attscale Sync="TRUE">0</attscale>
				<attrdefs Sync="TRUE">AGRRA</attrdefs>
				<attrdomv>
					<udom Sync="TRUE">Transect Average of % <i>Agaricia agaricites</i></udom>
				</attrdomv>
			</attr>
			
			<attr>
				<attrlabl Sync="TRUE">AAGASTD</attrlabl>
				<attalias Sync="TRUE">AAGASTD</attalias>
				<attrtype Sync="TRUE">String</attrtype>
				<attwidth Sync="TRUE">24</attwidth>
				<atprecis Sync="TRUE">0</atprecis>
				<attscale Sync="TRUE">0</attscale>
				<attrdefs Sync="TRUE">AGRRA</attrdefs>
				<attrdomv>
					<udom Sync="TRUE">Transect Std. Deviation of % <i>Agaricia agaricites</i></udom>
				</attrdomv>
			</attr>
			
			<attr>
				<attrlabl Sync="TRUE">ACERAVG</attrlabl>
				<attalias Sync="TRUE">ACERAVG</attalias>
				<attrtype Sync="TRUE">String</attrtype>
				<attwidth Sync="TRUE">24</attwidth>
				<atprecis Sync="TRUE">0</atprecis>
				<attscale Sync="TRUE">0</attscale>
				<attrdefs Sync="TRUE">AGRRA</attrdefs>
				<attrdomv>
					<udom Sync="TRUE">Transect Average of % <i>Acropora cervicornis</i></udom>
				</attrdomv>
			</attr>
			
			<attr>
				<attrlabl Sync="TRUE">ACERSTD</attrlabl>
				<attalias Sync="TRUE">ACERSTD</attalias>
				<attrtype Sync="TRUE">String</attrtype>
				<attwidth Sync="TRUE">24</attwidth>
				<atprecis Sync="TRUE">0</atprecis>
				<attscale Sync="TRUE">0</attscale>
				<attrdefs Sync="TRUE">AGRRA</attrdefs>
				<attrdomv>
					<udom Sync="TRUE">Transect Std. Deviation of % <i>Acropora cervicornis</i></udom>
				</attrdomv>
			</attr>
			
			<attr>
				<attrlabl Sync="TRUE">AGARAVG</attrlabl>
				<attalias Sync="TRUE">AGARAVG</attalias>
				<attrtype Sync="TRUE">String</attrtype>
				<attwidth Sync="TRUE">24</attwidth>
				<atprecis Sync="TRUE">0</atprecis>
				<attscale Sync="TRUE">0</attscale>
				<attrdefs Sync="TRUE">AGRRA</attrdefs>
				<attrdomv>
					<udom Sync="TRUE">Transect Average of % <i>Agaricia</i> sp.</udom>
				</attrdomv>
			</attr>
			
			<attr>
				<attrlabl Sync="TRUE">AGARSTD</attrlabl>
				<attalias Sync="TRUE">AGARSTD</attalias>
				<attrtype Sync="TRUE">String</attrtype>
				<attwidth Sync="TRUE">24</attwidth>
				<atprecis Sync="TRUE">0</atprecis>
				<attscale Sync="TRUE">0</attscale>
				<attrdefs Sync="TRUE">AGRRA</attrdefs>
				<attrdomv>
					<udom Sync="TRUE">Transect Std. Deviation of % <i>Agaricia</i> sp.</udom>
				</attrdomv>
			</attr>
			
			<attr>
				<attrlabl Sync="TRUE">AHUMAVG</attrlabl>
				<attalias Sync="TRUE">AHUMAVG</attalias>
				<attrtype Sync="TRUE">String</attrtype>
				<attwidth Sync="TRUE">24</attwidth>
				<atprecis Sync="TRUE">0</atprecis>
				<attscale Sync="TRUE">0</attscale>
				<attrdefs Sync="TRUE">AGRRA</attrdefs>
				<attrdomv>
					<udom Sync="TRUE">Transect Average of % <i>Agaricia humilis</i></udom>
				</attrdomv>
			</attr>
			
			<attr>
				<attrlabl Sync="TRUE">AHUMSTD</attrlabl>
				<attalias Sync="TRUE">AHUMSTD</attalias>
				<attrtype Sync="TRUE">String</attrtype>
				<attwidth Sync="TRUE">24</attwidth>
				<atprecis Sync="TRUE">0</atprecis>
				<attscale Sync="TRUE">0</attscale>
				<attrdefs Sync="TRUE">AGRRA</attrdefs>
				<attrdomv>
					<udom Sync="TRUE">Transect Std. Deviation of % <i>Agaricia humilis</i></udom>
				</attrdomv>
			</attr>
			
			<attr>
				<attrlabl Sync="TRUE">APALAVG</attrlabl>
				<attalias Sync="TRUE">APALAVG</attalias>
				<attrtype Sync="TRUE">String</attrtype>
				<attwidth Sync="TRUE">24</attwidth>
				<atprecis Sync="TRUE">0</atprecis>
				<attscale Sync="TRUE">0</attscale>
				<attrdefs Sync="TRUE">AGRRA</attrdefs>
				<attrdomv>
					<udom Sync="TRUE">Transect Average of % <i>Acropora palmata</i></udom>
				</attrdomv>
			</attr>
			
			<attr>
				<attrlabl Sync="TRUE">APALSTD</attrlabl>
				<attalias Sync="TRUE">APALSTD</attalias>
				<attrtype Sync="TRUE">String</attrtype>
				<attwidth Sync="TRUE">24</attwidth>
				<atprecis Sync="TRUE">0</atprecis>
				<attscale Sync="TRUE">0</attscale>
				<attrdefs Sync="TRUE">AGRRA</attrdefs>
				<attrdomv>
					<udom Sync="TRUE">Transect Std. Deviation of % <i>Acropora palmata</i></udom>
				</attrdomv>
			</attr>
			
			<attr>
				<attrlabl Sync="TRUE">ATENAVG</attrlabl>
				<attalias Sync="TRUE">ATENAVG</attalias>
				<attrtype Sync="TRUE">String</attrtype>
				<attwidth Sync="TRUE">24</attwidth>
				<atprecis Sync="TRUE">0</atprecis>
				<attscale Sync="TRUE">0</attscale>
				<attrdefs Sync="TRUE">AGRRA</attrdefs>
				<attrdomv>
					<udom Sync="TRUE">Transect Average of % <i>Agaricia tenuifolia</i></udom>
				</attrdomv>
			</attr>
			
			<attr>
				<attrlabl Sync="TRUE">ATENSTD</attrlabl>
				<attalias Sync="TRUE">ATENSTD</attalias>
				<attrtype Sync="TRUE">String</attrtype>
				<attwidth Sync="TRUE">24</attwidth>
				<atprecis Sync="TRUE">0</atprecis>
				<attscale Sync="TRUE">0</attscale>
				<attrdefs Sync="TRUE">AGRRA</attrdefs>
				<attrdomv>
					<udom Sync="TRUE">Transect Std. Deviation of % <i>Agaricia tenuifolia</i></udom>
				</attrdomv>
			</attr>
			
			<attr>
				<attrlabl Sync="TRUE">CNATAVG</attrlabl>
				<attalias Sync="TRUE">CNATAVG</attalias>
				<attrtype Sync="TRUE">String</attrtype>
				<attwidth Sync="TRUE">24</attwidth>
				<atprecis Sync="TRUE">0</atprecis>
				<attscale Sync="TRUE">0</attscale>
				<attrdefs Sync="TRUE">AGRRA</attrdefs>
				<attrdomv>
					<udom Sync="TRUE">Transect Average of % <i>Colpophyllia natans</i></udom>
				</attrdomv>
			</attr>
			
			<attr>
				<attrlabl Sync="TRUE">CNATSTD</attrlabl>
				<attalias Sync="TRUE">CNATSTD</attalias>
				<attrtype Sync="TRUE">String</attrtype>
				<attwidth Sync="TRUE">24</attwidth>
				<atprecis Sync="TRUE">0</atprecis>
				<attscale Sync="TRUE">0</attscale>
				<attrdefs Sync="TRUE">AGRRA</attrdefs>
				<attrdomv>
					<udom Sync="TRUE">Transect Std. Deviation of % <i>Colpophyllia natans</i></udom>
				</attrdomv>
			</attr>
			
			<attr>
				<attrlabl Sync="TRUE">DLABAVG</attrlabl>
				<attalias Sync="TRUE">DLABAVG</attalias>
				<attrtype Sync="TRUE">String</attrtype>
				<attwidth Sync="TRUE">24</attwidth>
				<atprecis Sync="TRUE">0</atprecis>
				<attscale Sync="TRUE">0</attscale>
				<attrdefs Sync="TRUE">AGRRA</attrdefs>
				<attrdomv>
					<udom Sync="TRUE">Transect Average of % <i>Diploria labyrinthiformis</i></udom>
				</attrdomv>
			</attr>
			
			<attr>
				<attrlabl Sync="TRUE">DLABSTD</attrlabl>
				<attalias Sync="TRUE">DLABSTD</attalias>
				<attrtype Sync="TRUE">String</attrtype>
				<attwidth Sync="TRUE">24</attwidth>
				<atprecis Sync="TRUE">0</atprecis>
				<attscale Sync="TRUE">0</attscale>
				<attrdefs Sync="TRUE">AGRRA</attrdefs>
				<attrdomv>
					<udom Sync="TRUE">Transect Std. Deviation of % <i>Diploria labyrinthiformis</i></udom>
				</attrdomv>
			</attr>
			
			<attr>
				<attrlabl Sync="TRUE">DSTOAVG</attrlabl>
				<attalias Sync="TRUE">DSTOAVG</attalias>
				<attrtype Sync="TRUE">String</attrtype>
				<attwidth Sync="TRUE">24</attwidth>
				<atprecis Sync="TRUE">0</atprecis>
				<attscale Sync="TRUE">0</attscale>
				<attrdefs Sync="TRUE">AGRRA</attrdefs>
				<attrdomv>
					<udom Sync="TRUE">Transect Average of % <i>Dichocoenia stokesii</i></udom>
				</attrdomv>
			</attr>
			
			<attr>
				<attrlabl Sync="TRUE">DSTOSTD</attrlabl>
				<attalias Sync="TRUE">DSTOSTD</attalias>
				<attrtype Sync="TRUE">String</attrtype>
				<attwidth Sync="TRUE">24</attwidth>
				<atprecis Sync="TRUE">0</atprecis>
				<attscale Sync="TRUE">0</attscale>
				<attrdefs Sync="TRUE">AGRRA</attrdefs>
				<attrdomv>
					<udom Sync="TRUE">Transect Std. Deviation of % <i>Dichocoenia stokesii</i></udom>
				</attrdomv>
			</attr>
			
			<attr>
				<attrlabl Sync="TRUE">EFASAVG</attrlabl>
				<attalias Sync="TRUE">EFASAVG</attalias>
				<attrtype Sync="TRUE">String</attrtype>
				<attwidth Sync="TRUE">24</attwidth>
				<atprecis Sync="TRUE">0</atprecis>
				<attscale Sync="TRUE">0</attscale>
				<attrdefs Sync="TRUE">AGRRA</attrdefs>
				<attrdomv>
					<udom Sync="TRUE">Transect Average of % <i>Eusmilia fastigiata</i></udom>
				</attrdomv>
			</attr>
			
			<attr>
				<attrlabl Sync="TRUE">EFASSTD</attrlabl>
				<attalias Sync="TRUE">EFASSTD</attalias>
				<attrtype Sync="TRUE">String</attrtype>
				<attwidth Sync="TRUE">24</attwidth>
				<atprecis Sync="TRUE">0</atprecis>
				<attscale Sync="TRUE">0</attscale>
				<attrdefs Sync="TRUE">AGRRA</attrdefs>
				<attrdomv>
					<udom Sync="TRUE">Transect Std. Deviation of % <i>Eusmilia fastigiata</i></udom>
				</attrdomv>
			</attr>
			
			<attr>
				<attrlabl Sync="TRUE">MALCAVG</attrlabl>
				<attalias Sync="TRUE">MALCAVG</attalias>
				<attrtype Sync="TRUE">String</attrtype>
				<attwidth Sync="TRUE">24</attwidth>
				<atprecis Sync="TRUE">0</atprecis>
				<attscale Sync="TRUE">0</attscale>
				<attrdefs Sync="TRUE">AGRRA</attrdefs>
				<attrdomv>
					<udom Sync="TRUE">Transect Average of % <i>Millepora alcicornis</i></udom>
				</attrdomv>
			</attr>
			
			<attr>
				<attrlabl Sync="TRUE">MALCSTD</attrlabl>
				<attalias Sync="TRUE">MALCSTD</attalias>
				<attrtype Sync="TRUE">String</attrtype>
				<attwidth Sync="TRUE">24</attwidth>
				<atprecis Sync="TRUE">0</atprecis>
				<attscale Sync="TRUE">0</attscale>
				<attrdefs Sync="TRUE">AGRRA</attrdefs>
				<attrdomv>
					<udom Sync="TRUE">Transect Std. Deviation of % <i>Millepora alcicornis</i></udom>
				</attrdomv>
			</attr>
			
			<attr>
				<attrlabl Sync="TRUE">MAURAVG</attrlabl>
				<attalias Sync="TRUE">MAURAVG</attalias>
				<attrtype Sync="TRUE">String</attrtype>
				<attwidth Sync="TRUE">24</attwidth>
				<atprecis Sync="TRUE">0</atprecis>
				<attscale Sync="TRUE">0</attscale>
				<attrdefs Sync="TRUE">AGRRA</attrdefs>
				<attrdomv>
					<udom Sync="TRUE">Transect Average of % <i>Madracis auretenra (mirabilis)</i></udom>
				</attrdomv>
			</attr>
			
			<attr>
				<attrlabl Sync="TRUE">MAURSTD</attrlabl>
				<attalias Sync="TRUE">MAURSTD</attalias>
				<attrtype Sync="TRUE">String</attrtype>
				<attwidth Sync="TRUE">24</attwidth>
				<atprecis Sync="TRUE">0</atprecis>
				<attscale Sync="TRUE">0</attscale>
				<attrdefs Sync="TRUE">AGRRA</attrdefs>
				<attrdomv>
					<udom Sync="TRUE">Transect Std. Deviation of % <i>Madracis auretenra (mirabilis)</i></udom>
				</attrdomv>
			</attr>
			
			<attr>
				<attrlabl Sync="TRUE">MCAVAVG</attrlabl>
				<attalias Sync="TRUE">MCAVAVG</attalias>
				<attrtype Sync="TRUE">String</attrtype>
				<attwidth Sync="TRUE">24</attwidth>
				<atprecis Sync="TRUE">0</atprecis>
				<attscale Sync="TRUE">0</attscale>
				<attrdefs Sync="TRUE">AGRRA</attrdefs>
				<attrdomv>
					<udom Sync="TRUE">Transect Average of % <i>Montastraea cavernosa</i></udom>
				</attrdomv>
			</attr>
			
			<attr>
				<attrlabl Sync="TRUE">MCAVSTD</attrlabl>
				<attalias Sync="TRUE">MCAVSTD</attalias>
				<attrtype Sync="TRUE">String</attrtype>
				<attwidth Sync="TRUE">24</attwidth>
				<atprecis Sync="TRUE">0</atprecis>
				<attscale Sync="TRUE">0</attscale>
				<attrdefs Sync="TRUE">AGRRA</attrdefs>
				<attrdomv>
					<udom Sync="TRUE">Transect Std. Deviation of % <i>Montastraea cavernosa</i></udom>
				</attrdomv>
			</attr>
			
			<attr>
				<attrlabl Sync="TRUE">MCOMAVG</attrlabl>
				<attalias Sync="TRUE">MCOMAVG</attalias>
				<attrtype Sync="TRUE">String</attrtype>
				<attwidth Sync="TRUE">24</attwidth>
				<atprecis Sync="TRUE">0</atprecis>
				<attscale Sync="TRUE">0</attscale>
				<attrdefs Sync="TRUE">AGRRA</attrdefs>
				<attrdomv>
					<udom Sync="TRUE">Transect Average of % <i>Millepora complanata</i></udom>
				</attrdomv>
			</attr>
			
			<attr>
				<attrlabl Sync="TRUE">MCOMSTD</attrlabl>
				<attalias Sync="TRUE">MCOMSTD</attalias>
				<attrtype Sync="TRUE">String</attrtype>
				<attwidth Sync="TRUE">24</attwidth>
				<atprecis Sync="TRUE">0</atprecis>
				<attscale Sync="TRUE">0</attscale>
				<attrdefs Sync="TRUE">AGRRA</attrdefs>
				<attrdomv>
					<udom Sync="TRUE">Transect Std. Deviation of % <i>Millepora complanata</i></udom>
				</attrdomv>
			</attr>
			
			<attr>
				<attrlabl Sync="TRUE">MDECAVG</attrlabl>
				<attalias Sync="TRUE">MDECAVG</attalias>
				<attrtype Sync="TRUE">String</attrtype>
				<attwidth Sync="TRUE">24</attwidth>
				<atprecis Sync="TRUE">0</atprecis>
				<attscale Sync="TRUE">0</attscale>
				<attrdefs Sync="TRUE">AGRRA</attrdefs>
				<attrdomv>
					<udom Sync="TRUE">Transect Average of % <i>Madracis decactis</i></udom>
				</attrdomv>
			</attr>
			
			<attr>
				<attrlabl Sync="TRUE">MDECSTD</attrlabl>
				<attalias Sync="TRUE">MDECSTD</attalias>
				<attrtype Sync="TRUE">String</attrtype>
				<attwidth Sync="TRUE">24</attwidth>
				<atprecis Sync="TRUE">0</atprecis>
				<attscale Sync="TRUE">0</attscale>
				<attrdefs Sync="TRUE">AGRRA</attrdefs>
				<attrdomv>
					<udom Sync="TRUE">Transect Std. Deviation of % <i>Madracis decactis</i></udom>
				</attrdomv>
			</attr>
			
			<attr>
				<attrlabl Sync="TRUE">MILLAVG</attrlabl>
				<attalias Sync="TRUE">MILLAVG</attalias>
				<attrtype Sync="TRUE">String</attrtype>
				<attwidth Sync="TRUE">24</attwidth>
				<atprecis Sync="TRUE">0</atprecis>
				<attscale Sync="TRUE">0</attscale>
				<attrdefs Sync="TRUE">AGRRA</attrdefs>
				<attrdomv>
					<udom Sync="TRUE">Transect Average of % <i>Millepora</i> sp.</udom>
				</attrdomv>
			</attr>
			
			<attr>
				<attrlabl Sync="TRUE">MILLSTD</attrlabl>
				<attalias Sync="TRUE">MILLSTD</attalias>
				<attrtype Sync="TRUE">String</attrtype>
				<attwidth Sync="TRUE">24</attwidth>
				<atprecis Sync="TRUE">0</atprecis>
				<attscale Sync="TRUE">0</attscale>
				<attrdefs Sync="TRUE">AGRRA</attrdefs>
				<attrdomv>
					<udom Sync="TRUE">Transect Std. Deviation of % <i>Millepora</i> sp.</udom>
				</attrdomv>
			</attr>
			
			<attr>
				<attrlabl Sync="TRUE">MMEAAVG</attrlabl>
				<attalias Sync="TRUE">MMEAAVG</attalias>
				<attrtype Sync="TRUE">String</attrtype>
				<attwidth Sync="TRUE">24</attwidth>
				<atprecis Sync="TRUE">0</atprecis>
				<attscale Sync="TRUE">0</attscale>
				<attrdefs Sync="TRUE">AGRRA</attrdefs>
				<attrdomv>
					<udom Sync="TRUE">Transect Average of % <i>Meandrina meandrites</i></udom>
				</attrdomv>
			</attr>
			
			<attr>
				<attrlabl Sync="TRUE">MMEASTD</attrlabl>
				<attalias Sync="TRUE">MMEASTD</attalias>
				<attrtype Sync="TRUE">String</attrtype>
				<attwidth Sync="TRUE">24</attwidth>
				<atprecis Sync="TRUE">0</atprecis>
				<attscale Sync="TRUE">0</attscale>
				<attrdefs Sync="TRUE">AGRRA</attrdefs>
				<attrdomv>
					<udom Sync="TRUE">Transect Std. Deviation of % <i>Meandrina meandrites</i></udom>
				</attrdomv>
			</attr>
			
			<attr>
				<attrlabl Sync="TRUE">OANNAVG</attrlabl>
				<attalias Sync="TRUE">OANNAVG</attalias>
				<attrtype Sync="TRUE">String</attrtype>
				<attwidth Sync="TRUE">24</attwidth>
				<atprecis Sync="TRUE">0</atprecis>
				<attscale Sync="TRUE">0</attscale>
				<attrdefs Sync="TRUE">AGRRA</attrdefs>
				<attrdomv>
					<udom Sync="TRUE">Transect Average of % <i>Orbicella annularis</i></udom>
				</attrdomv>
			</attr>
			
			<attr>
				<attrlabl Sync="TRUE">OANNSTD</attrlabl>
				<attalias Sync="TRUE">OANNSTD</attalias>
				<attrtype Sync="TRUE">String</attrtype>
				<attwidth Sync="TRUE">24</attwidth>
				<atprecis Sync="TRUE">0</atprecis>
				<attscale Sync="TRUE">0</attscale>
				<attrdefs Sync="TRUE">AGRRA</attrdefs>
				<attrdomv>
					<udom Sync="TRUE">Transect Std. Deviation of % <i>Orbicella annularis</i></udom>
				</attrdomv>
			</attr>
			
			<attr>
				<attrlabl Sync="TRUE">OFAVAVG</attrlabl>
				<attalias Sync="TRUE">OFAVAVG</attalias>
				<attrtype Sync="TRUE">String</attrtype>
				<attwidth Sync="TRUE">24</attwidth>
				<atprecis Sync="TRUE">0</atprecis>
				<attscale Sync="TRUE">0</attscale>
				<attrdefs Sync="TRUE">AGRRA</attrdefs>
				<attrdomv>
					<udom Sync="TRUE">Transect Average of % <i>Orbicella faveolata</i></udom>
				</attrdomv>
			</attr>
			
			<attr>
				<attrlabl Sync="TRUE">OFAVSTD</attrlabl>
				<attalias Sync="TRUE">OFAVSTD</attalias>
				<attrtype Sync="TRUE">String</attrtype>
				<attwidth Sync="TRUE">24</attwidth>
				<atprecis Sync="TRUE">0</atprecis>
				<attscale Sync="TRUE">0</attscale>
				<attrdefs Sync="TRUE">AGRRA</attrdefs>
				<attrdomv>
					<udom Sync="TRUE">Transect Std. Deviation of % <i>Orbicella faveolata</i></udom>
				</attrdomv>
			</attr>
			
			<attr>
				<attrlabl Sync="TRUE">OFRAAVG</attrlabl>
				<attalias Sync="TRUE">OFRAAVG</attalias>
				<attrtype Sync="TRUE">String</attrtype>
				<attwidth Sync="TRUE">24</attwidth>
				<atprecis Sync="TRUE">0</atprecis>
				<attscale Sync="TRUE">0</attscale>
				<attrdefs Sync="TRUE">AGRRA</attrdefs>
				<attrdomv>
					<udom Sync="TRUE">Transect Average of % <i>Orbicella franksi</i></udom>
				</attrdomv>
			</attr>
			
			<attr>
				<attrlabl Sync="TRUE">OFRASTD</attrlabl>
				<attalias Sync="TRUE">OFRASTD</attalias>
				<attrtype Sync="TRUE">String</attrtype>
				<attwidth Sync="TRUE">24</attwidth>
				<atprecis Sync="TRUE">0</atprecis>
				<attscale Sync="TRUE">0</attscale>
				<attrdefs Sync="TRUE">AGRRA</attrdefs>
				<attrdomv>
					<udom Sync="TRUE">Transect Std. Deviation of % <i>Orbicella franksi</i></udom>
				</attrdomv>
			</attr>
			
			<attr>
				<attrlabl Sync="TRUE">PASTAVG</attrlabl>
				<attalias Sync="TRUE">PASTAVG</attalias>
				<attrtype Sync="TRUE">String</attrtype>
				<attwidth Sync="TRUE">24</attwidth>
				<atprecis Sync="TRUE">0</atprecis>
				<attscale Sync="TRUE">0</attscale>
				<attrdefs Sync="TRUE">AGRRA</attrdefs>
				<attrdomv>
					<udom Sync="TRUE">Transect Average of % <i>Porites astreoides</i></udom>
				</attrdomv>
			</attr>
			
			<attr>
				<attrlabl Sync="TRUE">PASTSTD</attrlabl>
				<attalias Sync="TRUE">PASTSTD</attalias>
				<attrtype Sync="TRUE">String</attrtype>
				<attwidth Sync="TRUE">24</attwidth>
				<atprecis Sync="TRUE">0</atprecis>
				<attscale Sync="TRUE">0</attscale>
				<attrdefs Sync="TRUE">AGRRA</attrdefs>
				<attrdomv>
					<udom Sync="TRUE">Transect Std. Deviation of % <i>Porites astreoides</i></udom>
				</attrdomv>
			</attr>
			
			<attr>
				<attrlabl Sync="TRUE">PDIVAVG</attrlabl>
				<attalias Sync="TRUE">PDIVAVG</attalias>
				<attrtype Sync="TRUE">String</attrtype>
				<attwidth Sync="TRUE">24</attwidth>
				<atprecis Sync="TRUE">0</atprecis>
				<attscale Sync="TRUE">0</attscale>
				<attrdefs Sync="TRUE">AGRRA</attrdefs>
				<attrdomv>
					<udom Sync="TRUE">Transect Average of % <i>Porites divaricata</i></udom>
				</attrdomv>
			</attr>
			
			<attr>
				<attrlabl Sync="TRUE">PDIVSTD</attrlabl>
				<attalias Sync="TRUE">PDIVSTD</attalias>
				<attrtype Sync="TRUE">String</attrtype>
				<attwidth Sync="TRUE">24</attwidth>
				<atprecis Sync="TRUE">0</atprecis>
				<attscale Sync="TRUE">0</attscale>
				<attrdefs Sync="TRUE">AGRRA</attrdefs>
				<attrdomv>
					<udom Sync="TRUE">Transect Std. Deviation of % <i>Porites divaricata</i></udom>
				</attrdomv>
			</attr>
			
			<attr>
				<attrlabl Sync="TRUE">PFURAVG</attrlabl>
				<attalias Sync="TRUE">PFURAVG</attalias>
				<attrtype Sync="TRUE">String</attrtype>
				<attwidth Sync="TRUE">24</attwidth>
				<atprecis Sync="TRUE">0</atprecis>
				<attscale Sync="TRUE">0</attscale>
				<attrdefs Sync="TRUE">AGRRA</attrdefs>
				<attrdomv>
					<udom Sync="TRUE">Transect Average of % <i>Porites furcata</i></udom>
				</attrdomv>
			</attr>
			
			<attr>
				<attrlabl Sync="TRUE">PFURSTD</attrlabl>
				<attalias Sync="TRUE">PFURSTD</attalias>
				<attrtype Sync="TRUE">String</attrtype>
				<attwidth Sync="TRUE">24</attwidth>
				<atprecis Sync="TRUE">0</atprecis>
				<attscale Sync="TRUE">0</attscale>
				<attrdefs Sync="TRUE">AGRRA</attrdefs>
				<attrdomv>
					<udom Sync="TRUE">Transect Std. Deviation of % <i>Porites furcata</i></udom>
				</attrdomv>
			</attr>
			
			<attr>
				<attrlabl Sync="TRUE">PLCIAVG</attrlabl>
				<attalias Sync="TRUE">PLCIAVG</attalias>
				<attrtype Sync="TRUE">String</attrtype>
				<attwidth Sync="TRUE">24</attwidth>
				<atprecis Sync="TRUE">0</atprecis>
				<attscale Sync="TRUE">0</attscale>
				<attrdefs Sync="TRUE">AGRRA</attrdefs>
				<attrdomv>
					<udom Sync="TRUE"></udom>
				</attrdomv>
			</attr>
			
			<attr>
				<attrlabl Sync="TRUE">PLCISTD</attrlabl>
				<attalias Sync="TRUE">PLCISTD</attalias>
				<attrtype Sync="TRUE">String</attrtype>
				<attwidth Sync="TRUE">24</attwidth>
				<atprecis Sync="TRUE">0</atprecis>
				<attscale Sync="TRUE">0</attscale>
				<attrdefs Sync="TRUE">AGRRA</attrdefs>
				<attrdomv>
					<udom Sync="TRUE"></udom>
				</attrdomv>
			</attr>
			
			<attr>
				<attrlabl Sync="TRUE">PORIAVG</attrlabl>
				<attalias Sync="TRUE">PORIAVG</attalias>
				<attrtype Sync="TRUE">String</attrtype>
				<attwidth Sync="TRUE">24</attwidth>
				<atprecis Sync="TRUE">0</atprecis>
				<attscale Sync="TRUE">0</attscale>
				<attrdefs Sync="TRUE">AGRRA</attrdefs>
				<attrdomv>
					<udom Sync="TRUE">Transect Average of % <i>Porites</i> sp.</udom>
				</attrdomv>
			</attr>
			
			<attr>
				<attrlabl Sync="TRUE">PORISTD</attrlabl>
				<attalias Sync="TRUE">PORISTD</attalias>
				<attrtype Sync="TRUE">String</attrtype>
				<attwidth Sync="TRUE">24</attwidth>
				<atprecis Sync="TRUE">0</atprecis>
				<attscale Sync="TRUE">0</attscale>
				<attrdefs Sync="TRUE">AGRRA</attrdefs>
				<attrdomv>
					<udom Sync="TRUE">Transect Std. Deviation of % <i>Porites</i> sp.</udom>
				</attrdomv>
			</attr>
			
			<attr>
				<attrlabl Sync="TRUE">PPORAVG</attrlabl>
				<attalias Sync="TRUE">PPORAVG</attalias>
				<attrtype Sync="TRUE">String</attrtype>
				<attwidth Sync="TRUE">24</attwidth>
				<atprecis Sync="TRUE">0</atprecis>
				<attscale Sync="TRUE">0</attscale>
				<attrdefs Sync="TRUE">AGRRA</attrdefs>
				<attrdomv>
					<udom Sync="TRUE">Transect Average of % <i>Porites porites</i></udom>
				</attrdomv>
			</attr>
			
			<attr>
				<attrlabl Sync="TRUE">PPORSTD</attrlabl>
				<attalias Sync="TRUE">PPORSTD</attalias>
				<attrtype Sync="TRUE">String</attrtype>
				<attwidth Sync="TRUE">24</attwidth>
				<atprecis Sync="TRUE">0</atprecis>
				<attscale Sync="TRUE">0</attscale>
				<attrdefs Sync="TRUE">AGRRA</attrdefs>
				<attrdomv>
					<udom Sync="TRUE">Transect Std. Deviation of % <i>Porites porites</i></udom>
				</attrdomv>
			</attr>
			
			<attr>
				<attrlabl Sync="TRUE">PSTRAVG</attrlabl>
				<attalias Sync="TRUE">PSTRAVG</attalias>
				<attrtype Sync="TRUE">String</attrtype>
				<attwidth Sync="TRUE">24</attwidth>
				<atprecis Sync="TRUE">0</atprecis>
				<attscale Sync="TRUE">0</attscale>
				<attrdefs Sync="TRUE">AGRRA</attrdefs>
				<attrdomv>
					<udom Sync="TRUE">Transect Average of % <i>Pseudodiploria strigosa</i></udom>
				</attrdomv>
			</attr>
			
			<attr>
				<attrlabl Sync="TRUE">PSTRSTD</attrlabl>
				<attalias Sync="TRUE">PSTRSTD</attalias>
				<attrtype Sync="TRUE">String</attrtype>
				<attwidth Sync="TRUE">24</attwidth>
				<atprecis Sync="TRUE">0</atprecis>
				<attscale Sync="TRUE">0</attscale>
				<attrdefs Sync="TRUE">AGRRA</attrdefs>
				<attrdomv>
					<udom Sync="TRUE">Transect Std. Deviation of % <i>Pseudodiploria strigosa</i></udom>
				</attrdomv>
			</attr>
			
			<attr>
				<attrlabl Sync="TRUE">SINTAVG</attrlabl>
				<attalias Sync="TRUE">SINTAVG</attalias>
				<attrtype Sync="TRUE">String</attrtype>
				<attwidth Sync="TRUE">24</attwidth>
				<atprecis Sync="TRUE">0</atprecis>
				<attscale Sync="TRUE">0</attscale>
				<attrdefs Sync="TRUE">AGRRA</attrdefs>
				<attrdomv>
					<udom Sync="TRUE">Transect Average of % <i>Stephanocoenia intersepta</i></udom>
				</attrdomv>
			</attr>
			
			<attr>
				<attrlabl Sync="TRUE">SINTSTD</attrlabl>
				<attalias Sync="TRUE">SINTSTD</attalias>
				<attrtype Sync="TRUE">String</attrtype>
				<attwidth Sync="TRUE">24</attwidth>
				<atprecis Sync="TRUE">0</atprecis>
				<attscale Sync="TRUE">0</attscale>
				<attrdefs Sync="TRUE">AGRRA</attrdefs>
				<attrdomv>
					<udom Sync="TRUE">Transect Std. Deviation of % <i>Stephanocoenia intersepta</i></udom>
				</attrdomv>
			</attr>
			
			<attr>
				<attrlabl Sync="TRUE">SRADAVG</attrlabl>
				<attalias Sync="TRUE">SRADAVG</attalias>
				<attrtype Sync="TRUE">String</attrtype>
				<attwidth Sync="TRUE">24</attwidth>
				<atprecis Sync="TRUE">0</atprecis>
				<attscale Sync="TRUE">0</attscale>
				<attrdefs Sync="TRUE">AGRRA</attrdefs>
				<attrdomv>
					<udom Sync="TRUE">Transect Average of % <i>Siderastrea radians</i></udom>
				</attrdomv>
			</attr>
			
			<attr>
				<attrlabl Sync="TRUE">SRADSTD</attrlabl>
				<attalias Sync="TRUE">SRADSTD</attalias>
				<attrtype Sync="TRUE">String</attrtype>
				<attwidth Sync="TRUE">24</attwidth>
				<atprecis Sync="TRUE">0</atprecis>
				<attscale Sync="TRUE">0</attscale>
				<attrdefs Sync="TRUE">AGRRA</attrdefs>
				<attrdomv>
					<udom Sync="TRUE">Transect Std. Deviation of % <i>Siderastrea radians</i></udom>
				</attrdomv>
			</attr>
			
			<attr>
				<attrlabl Sync="TRUE">SSIDAVG</attrlabl>
				<attalias Sync="TRUE">SSIDAVG</attalias>
				<attrtype Sync="TRUE">String</attrtype>
				<attwidth Sync="TRUE">24</attwidth>
				<atprecis Sync="TRUE">0</atprecis>
				<attscale Sync="TRUE">0</attscale>
				<attrdefs Sync="TRUE">AGRRA</attrdefs>
				<attrdomv>
					<udom Sync="TRUE">Transect Average of % <i>Siderastrea siderea</i></udom>
				</attrdomv>
			</attr>
			
			<attr>
				<attrlabl Sync="TRUE">SSIDSTD</attrlabl>
				<attalias Sync="TRUE">SSIDSTD</attalias>
				<attrtype Sync="TRUE">String</attrtype>
				<attwidth Sync="TRUE">24</attwidth>
				<atprecis Sync="TRUE">0</atprecis>
				<attscale Sync="TRUE">0</attscale>
				<attrdefs Sync="TRUE">AGRRA</attrdefs>
				<attrdomv>
					<udom Sync="TRUE">Transect Std. Deviation of % <i>Siderastrea siderea</i></udom>
				</attrdomv>
			</attr>
			
		</detailed>
	</eainfo>
	<distInfo>
		<distTranOps>
			<onLineSrc>
				<linkage>www.agrra.org</linkage>
			</onLineSrc>
			<transSize Sync="TRUE">0.065</transSize>
		</distTranOps>
		<distFormat>
			<formatName Sync="TRUE">Shapefile</formatName>
		</distFormat>
	</distInfo>
	<dataIdInfo>
		<idCitation>
			<resTitle></resTitle>
			<resEd></resEd>
			<citRespParty>
				<rpOrgName></rpOrgName>
				<role>
					<RoleCd value="006"/>
				</role>
			</citRespParty>
			<presForm>
				<PresFormCd value="005" Sync="TRUE"/>
			</presForm>
		</idCitation>
		<idAbs></idAbs>
		<idPurp>The Atlantic and Gulf Rapid Reef Assessment (AGRRA) Program champions coral reef conservation and empowers those who protect these diverse ecosystems. We are an international collaboration of scientists, managers, and supporters aimed at improving the regional condition of reefs in the Western Atlantic and Gulf of Mexico. For 20 years, AGRRA has used an innovative regional approach to examine the condition of reef-building corals, algae and fishes and support the conservation of coral reef ecosystems. We curate and distribute data, research and educational materials that support this mission.<br></br>AGRRA’s Data Explorer houses the largest database on Caribbean coral reef health indicators, with data available from more than 2,000 reef areas in 28 countries throughout the Caribbean. You can explore the data through our database, ready-made spreadsheets and GIS shapefiles.</idPurp>
		<idCredit>AGRRA. 2018. Atlantic and Gulf Rapid Reef Assessment (AGRRA): An online database of AGRRA coral reef survey data. Available: http://agrra.org. (Accessed: Date [e.g., March 10, 2018]).</idCredit>
		<idPoC>
			<rpIndName></rpIndName>
			<rpCntInfo>
				<cntPhone>
					<voiceNum></voiceNum>
				</cntPhone>
				<cntInstr></cntInstr>
			</rpCntInfo>
			<role>
				<RoleCd value="007"/>
			</role>
		</idPoC>
		<resConst>
			<LegConsts>
				<othConsts></othConsts>
			</LegConsts>
		</resConst>
		<resConst>
			<Consts>
				<useLimit>By accessing and using any of the datasets distributed by AGRRA, you acknowledge that you have read, understood, and agree to comply with the terms and conditions contained within the AGRRA data usage agreement provided along with these shapefiles. AGRRA may amend these terms and conditions at any time. Your continued use of this data constitutes acceptance of the terms and conditions stated at the time of your use. You should contact AGRRA to determine the current terms and conditions to which you are bound.</useLimit>
			</Consts>
		</resConst>
	</dataIdInfo>
</metadata>
